langswitch
